{
  "updated": "2026-07-01T10:59:49.711536Z",
  "quotes": {
    "HCC": {
      "c": 81.16,
      "h": 82.56,
      "l": 80.26,
      "o": 81.57,
      "pc": 80.81,
      "t": 1782849600
    },
    "RIG": {
      "c": 4.89,
      "h": 5.17,
      "l": 4.88,
      "o": 5.06,
      "pc": 5.04,
      "t": 1782849600
    },
    "AMR": {
      "c": 164.94,
      "h": 166.96,
      "l": 161.9,
      "o": 165,
      "pc": 164.26,
      "t": 1782849600
    }
  },
  "costBasis": {
    "HCC": {
      "recent": {
        "buy": 79.96,
        "low": 75.71,
        "high": 105.15,
        "quarter": "2026 Q1",
        "source": "yahoo"
      },
      "allTime": {
        "avg": 64.99,
        "quarters": 10,
        "first": "2023 Q4",
        "last": "2026 Q1"
      }
    },
    "RIG": {
      "recent": {
        "buy": 3.31,
        "low": 3.07,
        "high": 4.56,
        "quarter": "2025 Q4",
        "source": "yahoo"
      },
      "allTime": {
        "avg": 4.5,
        "quarters": 3,
        "first": "2025 Q3",
        "last": "2026 Q1"
      }
    },
    "AMR": {
      "recent": {
        "buy": 169.63,
        "low": 155.5,
        "high": 253.82,
        "quarter": "2026 Q1",
        "source": "yahoo"
      },
      "allTime": {
        "avg": 215.76,
        "quarters": 12,
        "first": "2023 Q2",
        "last": "2026 Q1"
      }
    }
  }
}