{
  "updated": "2026-07-15T09:45:39.312313Z",
  "quotes": {
    "HCC": {
      "c": 83.33,
      "h": 84.55,
      "l": 82.02,
      "o": 84.43,
      "pc": 82.12,
      "t": 1784059200
    },
    "RIG": {
      "c": 5.31,
      "h": 5.51,
      "l": 5.25,
      "o": 5.46,
      "pc": 5.37,
      "t": 1784059200
    },
    "AMR": {
      "c": 153.94,
      "h": 155.75,
      "l": 151,
      "o": 151,
      "pc": 148.7,
      "t": 1784059200
    }
  },
  "costBasis": {
    "HCC": {
      "recent": {
        "buy": 79.96,
        "low": 75.71,
        "high": 105.15,
        "quarter": "2026 Q1",
        "source": "yahoo"
      },
      "allTime": {
        "avg": 64.99,
        "quarters": 10,
        "first": "2023 Q4",
        "last": "2026 Q1"
      }
    },
    "RIG": {
      "recent": {
        "buy": 3.31,
        "low": 3.07,
        "high": 4.56,
        "quarter": "2025 Q4",
        "source": "yahoo"
      },
      "allTime": {
        "avg": 4.5,
        "quarters": 3,
        "first": "2025 Q3",
        "last": "2026 Q1"
      }
    },
    "AMR": {
      "recent": {
        "buy": 169.63,
        "low": 155.5,
        "high": 253.82,
        "quarter": "2026 Q1",
        "source": "yahoo"
      },
      "allTime": {
        "avg": 215.76,
        "quarters": 12,
        "first": "2023 Q2",
        "last": "2026 Q1"
      }
    }
  }
}