{
  "updated": "2026-06-23T21:21:28.086470Z",
  "quotes": {
    "GOOGL": {
      "c": 346.1,
      "h": 349.29,
      "l": 340.2,
      "o": 340.85,
      "pc": 349.68,
      "t": 1782231417
    },
    "GOOG": {
      "c": 345.5,
      "h": 348.72,
      "l": 339.71,
      "o": 340.48,
      "pc": 348.78,
      "t": 1782231416
    },
    "PDD": {
      "c": 75.96,
      "h": 77.5,
      "l": 75.7,
      "o": 76.44,
      "pc": 78.11,
      "t": 1782231407
    },
    "BRK.B": {
      "c": 492.83,
      "h": 494.34,
      "l": 489.46,
      "o": 489.46,
      "pc": 488.69,
      "t": 1782231413
    },
    "EWBC": {
      "c": 130.67,
      "h": 130.85,
      "l": 125.38,
      "o": 127.23,
      "pc": 129.13,
      "t": 1782231396
    },
    "BAC": {
      "c": 57.83,
      "h": 57.88,
      "l": 57.2,
      "o": 57.4,
      "pc": 57.37,
      "t": 1782231415
    },
    "OXY": {
      "c": 52.31,
      "h": 52.48,
      "l": 51.66,
      "o": 51.8,
      "pc": 52,
      "t": 1782231415
    },
    "CROX": {
      "c": 121.28,
      "h": 121.76,
      "l": 118.02,
      "o": 120.72,
      "pc": 123.8,
      "t": 1782231382
    },
    "TME": {
      "c": 8.27,
      "h": 8.37,
      "l": 8.1,
      "o": 8.27,
      "pc": 8.34,
      "t": 1782231403
    },
    "SPGI": {
      "c": 401.41,
      "h": 415,
      "l": 400.79,
      "o": 409.96,
      "pc": 407.39,
      "t": 1782231396
    },
    "HRB": {
      "c": 35.37,
      "h": 35.44,
      "l": 34.46,
      "o": 34.46,
      "pc": 34.04,
      "t": 1782231417
    },
    "MCO": {
      "c": 443.55,
      "h": 452.39,
      "l": 443.15,
      "o": 449.01,
      "pc": 447.33,
      "t": 1782231414
    },
    "AAPL": {
      "c": 298.47,
      "h": 301.64,
      "l": 295.18,
      "o": 296.21,
      "pc": 297.01,
      "t": 1782231417
    },
    "MSCI": {
      "c": 586.57,
      "h": 590.12,
      "l": 579.73,
      "o": 579.73,
      "pc": 580.85,
      "t": 1782231408
    }
  },
  "costBasis": {
    "GOOGL": {
      "recent": {
        "buy": 284.65,
        "low": 271.95,
        "high": 348.55,
        "quarter": "2026 Q1",
        "source": "yahoo"
      },
      "allTime": {
        "avg": 174.9,
        "quarters": 16,
        "first": "2022 Q2",
        "last": "2026 Q1"
      }
    },
    "GOOG": {
      "recent": {
        "buy": 251.01,
        "low": 236.22,
        "high": 328.03,
        "quarter": "2025 Q4",
        "source": "yahoo"
      },
      "allTime": {
        "avg": 205.0,
        "quarters": 24,
        "first": "2020 Q2",
        "last": "2026 Q1"
      }
    },
    "PDD": {
      "recent": {
        "buy": 92.46,
        "low": 87.11,
        "high": 125.4,
        "quarter": "2025 Q2",
        "source": "yahoo"
      },
      "allTime": {
        "avg": 101.97,
        "quarters": 4,
        "first": "2025 Q2",
        "last": "2026 Q1"
      }
    },
    "BRK.B": {
      "recent": {
        "buy": 303.26,
        "low": 294.81,
        "high": 362.1,
        "quarter": "2022 Q1",
        "source": "yahoo"
      },
      "allTime": {
        "avg": 375.7,
        "quarters": 17,
        "first": "2022 Q1",
        "last": "2026 Q1"
      }
    },
    "EWBC": {
      "recent": {
        "buy": 40.49,
        "low": 37.88,
        "high": 52.72,
        "quarter": "2023 Q2",
        "source": "yahoo"
      },
      "allTime": {
        "avg": 83.46,
        "quarters": 13,
        "first": "2023 Q1",
        "last": "2026 Q1"
      }
    },
    "BAC": {
      "recent": {
        "buy": 26.05,
        "low": 24.22,
        "high": 33.83,
        "quarter": "2023 Q1",
        "source": "yahoo"
      },
      "allTime": {
        "avg": 36.21,
        "quarters": 25,
        "first": "2020 Q1",
        "last": "2026 Q1"
      }
    },
    "OXY": {
      "recent": {
        "buy": 57.97,
        "low": 56.48,
        "high": 68.15,
        "quarter": "2024 Q2",
        "source": "yahoo"
      },
      "allTime": {
        "avg": 51.09,
        "quarters": 8,
        "first": "2024 Q2",
        "last": "2026 Q1"
      }
    },
    "CROX": {
      "recent": {
        "buy": 78.3,
        "low": 75.13,
        "high": 101.59,
        "quarter": "2026 Q1",
        "source": "yahoo"
      },
      "allTime": {
        "avg": 84.06,
        "quarters": 2,
        "first": "2025 Q4",
        "last": "2026 Q1"
      }
    },
    "TME": {
      "recent": {
        "buy": 10.63,
        "low": 8.98,
        "high": 18.24,
        "quarter": "2026 Q1",
        "source": "yahoo"
      },
      "allTime": {
        "avg": 9.28,
        "quarters": 1,
        "first": "2026 Q1",
        "last": "2026 Q1"
      }
    },
    "SPGI": {
      "recent": {
        "buy": 404.83,
        "low": 379.84,
        "high": 549.69,
        "quarter": "2026 Q1",
        "source": "yahoo"
      },
      "allTime": {
        "avg": 425.34,
        "quarters": 1,
        "first": "2026 Q1",
        "last": "2026 Q1"
      }
    },
    "HRB": {
      "recent": {
        "buy": 29.49,
        "low": 27.48,
        "high": 44.15,
        "quarter": "2026 Q1",
        "source": "yahoo"
      },
      "allTime": {
        "avg": 31.74,
        "quarters": 1,
        "first": "2026 Q1",
        "last": "2026 Q1"
      }
    },
    "MCO": {
      "recent": {
        "buy": 421.87,
        "low": 400.46,
        "high": 544.4,
        "quarter": "2026 Q1",
        "source": "yahoo"
      },
      "allTime": {
        "avg": 436.25,
        "quarters": 1,
        "first": "2026 Q1",
        "last": "2026 Q1"
      }
    },
    "AAPL": {
      "recent": {
        "buy": 107.85,
        "low": 104.1,
        "high": 134.85,
        "quarter": "2020 Q4",
        "source": "yahoo"
      },
      "allTime": {
        "avg": 167.41,
        "quarters": 22,
        "first": "2020 Q4",
        "last": "2026 Q1"
      }
    },
    "MSCI": {
      "recent": {
        "buy": 516.47,
        "low": 497.32,
        "high": 621.58,
        "quarter": "2026 Q1",
        "source": "yahoo"
      },
      "allTime": {
        "avg": 539.01,
        "quarters": 1,
        "first": "2026 Q1",
        "last": "2026 Q1"
      }
    }
  }
}