{
  "MA": {
    "quote": 499.66,
    "costBasis": 499.66,
    "source": "13f-estimate"
  },
  "BN": {
    "quote": 40.47,
    "costBasis": 40.47,
    "source": "13f-estimate"
  },
  "KKR": {
    "quote": 92.5,
    "costBasis": 92.5,
    "source": "13f-estimate"
  },
  "MCO": {
    "quote": 436.25,
    "costBasis": 436.25,
    "source": "13f-estimate"
  },
  "V": {
    "quote": 302.24,
    "costBasis": 302.24,
    "source": "13f-estimate"
  },
  "ROP": {
    "quote": 353.86,
    "costBasis": 353.86,
    "source": "13f-estimate"
  },
  "CSGP": {
    "quote": 40.34,
    "costBasis": 40.34,
    "source": "13f-estimate"
  },
  "FICO": {
    "quote": 1067.54,
    "costBasis": 1067.54,
    "source": "13f-estimate"
  },
  "ORLY": {
    "quote": 92.31,
    "costBasis": 92.31,
    "source": "13f-estimate"
  },
  "CPRT": {
    "quote": 33.2,
    "costBasis": 33.2,
    "source": "13f-estimate"
  },
  "ABNB": {
    "quote": 126.28,
    "costBasis": 126.28,
    "source": "13f-estimate"
  },
  "CCCS": {
    "quote": 6.0,
    "costBasis": 6.0,
    "source": "13f-estimate"
  },
  "CRM": {
    "quote": 186.67,
    "costBasis": 186.67,
    "source": "13f-estimate"
  },
  "NOW": {
    "quote": 104.55,
    "costBasis": 104.55,
    "source": "13f-estimate"
  },
  "GSHD": {
    "quote": 42.66,
    "costBasis": 42.66,
    "source": "13f-estimate"
  },
  "SOPH": {
    "quote": 4.95,
    "costBasis": 4.95,
    "source": "13f-estimate"
  },
  "AMT": {
    "quote": 172.58,
    "costBasis": 172.58,
    "source": "13f-estimate"
  },
  "PRM": {
    "quote": 24.42,
    "costBasis": 24.42,
    "source": "13f-estimate"
  },
  "BRK.B": {
    "quote": 479.2,
    "costBasis": 479.2,
    "source": "13f-estimate"
  }
}
