{
  "updated": "2026-06-13T15:24:54.764544Z",
  "quotes": {
    "AMZN": {
      "c": 238.57,
      "h": 243.36,
      "l": 233.59,
      "o": 243.22,
      "pc": 241.51,
      "t": 1781294400
    },
    "MU": {
      "c": 981.63,
      "h": 1012.62,
      "l": 960.19,
      "o": 971.82,
      "pc": 995.87,
      "t": 1781294400
    },
    "GOOG": {
      "c": 358.18,
      "h": 364.77,
      "l": 353.34,
      "o": 361.11,
      "pc": 356.56,
      "t": 1781294400
    },
    "UBER": {
      "c": 68.87,
      "h": 70.23,
      "l": 67.4,
      "o": 70.03,
      "pc": 69.55,
      "t": 1781294400
    },
    "TSM": {
      "c": 423.95,
      "h": 426.94,
      "l": 417.21,
      "o": 420.06,
      "pc": 421.07,
      "t": 1781294400
    },
    "BABA": {
      "c": 112.8,
      "h": 112.82,
      "l": 110.97,
      "o": 112.58,
      "pc": 112.69,
      "t": 1781294400
    },
    "VST": {
      "c": 148.04,
      "h": 150.5,
      "l": 147,
      "o": 148.01,
      "pc": 146.38,
      "t": 1781294400
    },
    "IEMG": {
      "c": 82.59,
      "h": 82.86,
      "l": 81.63,
      "o": 82.27,
      "pc": 82.07,
      "t": 1781294400
    },
    "NVDA": {
      "c": 205.21,
      "h": 207.07,
      "l": 203.44,
      "o": 204.87,
      "pc": 204.87,
      "t": 1781294400
    },
    "NRG": {
      "c": 125.49,
      "h": 130,
      "l": 123.9,
      "o": 125.19,
      "pc": 123.7,
      "t": 1781294400
    },
    "META": {
      "c": 567,
      "h": 576.07,
      "l": 560.9,
      "o": 572.96,
      "pc": 568.43,
      "t": 1781294400
    },
    "SNDK": {
      "c": 1980.12,
      "h": 2021.65,
      "l": 1865.11,
      "o": 1890.99,
      "pc": 1881.51,
      "t": 1781294400
    },
    "GLW": {
      "c": 179.22,
      "h": 180.77,
      "l": 173.41,
      "o": 178.01,
      "pc": 176.55,
      "t": 1781294400
    },
    "WHR": {
      "c": 42.9,
      "h": 43.51,
      "l": 41.9,
      "o": 42.74,
      "pc": 42.41,
      "t": 1781294400
    },
    "PDD": {
      "c": 81.58,
      "h": 82.28,
      "l": 80.43,
      "o": 81.87,
      "pc": 81.3,
      "t": 1781294400
    },
    "LRCX": {
      "c": 366.83,
      "h": 373.82,
      "l": 354.89,
      "o": 359.4,
      "pc": 362.52,
      "t": 1781294400
    },
    "BIDU": {
      "c": 115.79,
      "h": 117.38,
      "l": 114.65,
      "o": 116.84,
      "pc": 116.11,
      "t": 1781294400
    },
    "LHX": {
      "c": 307.81,
      "h": 313.3,
      "l": 306,
      "o": 312.94,
      "pc": 312.17,
      "t": 1781294400
    },
    "RTX": {
      "c": 183.55,
      "h": 184.87,
      "l": 181.87,
      "o": 184.7,
      "pc": 184.21,
      "t": 1781294400
    },
    "ASML": {
      "c": 1863.57,
      "h": 1892.8,
      "l": 1839,
      "o": 1847.62,
      "pc": 1899.48,
      "t": 1781294400
    },
    "QCOM": {
      "c": 211.74,
      "h": 215.01,
      "l": 200.1,
      "o": 201.86,
      "pc": 202.96,
      "t": 1781294400
    },
    "BALL": {
      "c": 57,
      "h": 57.44,
      "l": 56.35,
      "o": 56.98,
      "pc": 56.34,
      "t": 1781294400
    },
    "AMD": {
      "c": 511.59,
      "h": 521.71,
      "l": 494,
      "o": 499.69,
      "pc": 488.45,
      "t": 1781294400
    },
    "JD": {
      "c": 28.57,
      "h": 28.73,
      "l": 28.39,
      "o": 28.71,
      "pc": 28.06,
      "t": 1781294400
    },
    "LYFT": {
      "c": 13.55,
      "h": 13.84,
      "l": 13.48,
      "o": 13.71,
      "pc": 13.71,
      "t": 1781294400
    },
    "MSFT": {
      "c": 390.76,
      "h": 391.74,
      "l": 382.27,
      "o": 391.44,
      "pc": 390.34,
      "t": 1781294400
    },
    "KWEB": {
      "c": 26.5,
      "h": 26.68,
      "l": 26.39,
      "o": 26.64,
      "pc": 26.57,
      "t": 1781294400
    },
    "ET": {
      "c": 19.08,
      "h": 19.22,
      "l": 18.68,
      "o": 18.78,
      "pc": 18.76,
      "t": 1781294400
    },
    "MPLX": {
      "c": 56.89,
      "h": 57.68,
      "l": 56.28,
      "o": 56.32,
      "pc": 56.49,
      "t": 1781294400
    },
    "UNH": {
      "c": 408.54,
      "h": 409.89,
      "l": 404.81,
      "o": 409.02,
      "pc": 405.55,
      "t": 1781294400
    },
    "DB": {
      "c": 33.32,
      "h": 33.33,
      "l": 32.78,
      "o": 33.07,
      "pc": 32.21,
      "t": 1781294400
    }
  },
  "costBasis": {
    "AMZN": {
      "recent": {
        "buy": 203.31,
        "low": 196.0,
        "high": 248.94,
        "quarter": "2026 Q1",
        "source": "yahoo"
      },
      "allTime": {
        "avg": 283.3,
        "quarters": 29,
        "first": "2019 Q1",
        "last": "2026 Q1"
      }
    },
    "MU": {
      "recent": {
        "buy": 324.05,
        "low": 294.74,
        "high": 471.14,
        "quarter": "2026 Q1",
        "source": "yahoo"
      },
      "allTime": {
        "avg": 44.53,
        "quarters": 36,
        "first": "2016 Q4",
        "last": "2026 Q1"
      }
    },
    "GOOG": {
      "recent": {
        "buy": 251.01,
        "low": 236.22,
        "high": 328.03,
        "quarter": "2025 Q4",
        "source": "yahoo"
      },
      "allTime": {
        "avg": 390.93,
        "quarters": 41,
        "first": "2016 Q1",
        "last": "2026 Q1"
      }
    },
    "UBER": {
      "recent": {
        "buy": 71.04,
        "low": 68.46,
        "high": 88.24,
        "quarter": "2026 Q1",
        "source": "yahoo"
      },
      "allTime": {
        "avg": 48.83,
        "quarters": 20,
        "first": "2021 Q2",
        "last": "2026 Q1"
      }
    },
    "TSM": {
      "recent": {
        "buy": 319.85,
        "low": 310.1,
        "high": 388.2,
        "quarter": "2026 Q1",
        "source": "yahoo"
      },
      "allTime": {
        "avg": 337.95,
        "quarters": 1,
        "first": "2026 Q1",
        "last": "2026 Q1"
      }
    },
    "BABA": {
      "recent": {
        "buy": 83.39,
        "low": 79.61,
        "high": 114.81,
        "quarter": "2024 Q4",
        "source": "yahoo"
      },
      "allTime": {
        "avg": 109.63,
        "quarters": 33,
        "first": "2017 Q2",
        "last": "2026 Q1"
      }
    },
    "VST": {
      "recent": {
        "buy": 145.39,
        "low": 138.34,
        "high": 182.31,
        "quarter": "2026 Q1",
        "source": "yahoo"
      },
      "allTime": {
        "avg": 149.98,
        "quarters": 7,
        "first": "2024 Q3",
        "last": "2026 Q1"
      }
    },
    "IEMG": {
      "recent": {
        "buy": 68.55,
        "low": 66.98,
        "high": 77.68,
        "quarter": "2026 Q1",
        "source": "yahoo"
      },
      "allTime": {
        "avg": 103.88,
        "quarters": 7,
        "first": "2020 Q4",
        "last": "2026 Q1"
      }
    },
    "NVDA": {
      "recent": {
        "buy": 158.07,
        "low": 151.29,
        "high": 184.31,
        "quarter": "2025 Q3",
        "source": "yahoo"
      },
      "allTime": {
        "avg": 110.35,
        "quarters": 13,
        "first": "2023 Q1",
        "last": "2026 Q1"
      }
    },
    "NRG": {
      "recent": {
        "buy": 144.69,
        "low": 139.46,
        "high": 189.38,
        "quarter": "2026 Q1",
        "source": "yahoo"
      },
      "allTime": {
        "avg": 45.12,
        "quarters": 14,
        "first": "2017 Q2",
        "last": "2026 Q1"
      }
    },
    "META": {
      "recent": {
        "buy": 606.26,
        "low": 580.28,
        "high": 757.89,
        "quarter": "2025 Q4",
        "source": "yahoo"
      },
      "allTime": {
        "avg": 1181.23,
        "quarters": 40,
        "first": "2016 Q1",
        "last": "2026 Q1"
      }
    },
    "SNDK": {
      "recent": {
        "buy": 339.91,
        "low": 244.0,
        "high": 777.6,
        "quarter": "2026 Q1",
        "source": "yahoo"
      },
      "allTime": {
        "avg": 635.34,
        "quarters": 1,
        "first": "2026 Q1",
        "last": "2026 Q1"
      }
    },
    "GLW": {
      "recent": {
        "buy": 39.51,
        "low": 36.7,
        "high": 51.75,
        "quarter": "2025 Q2",
        "source": "yahoo"
      },
      "allTime": {
        "avg": 57.34,
        "quarters": 6,
        "first": "2024 Q4",
        "last": "2026 Q1"
      }
    },
    "WHR": {
      "recent": {
        "buy": 79.27,
        "low": 75.09,
        "high": 108.05,
        "quarter": "2025 Q3",
        "source": "yahoo"
      },
      "allTime": {
        "avg": 82.05,
        "quarters": 12,
        "first": "2016 Q1",
        "last": "2026 Q1"
      }
    },
    "PDD": {
      "recent": {
        "buy": 100.97,
        "low": 94.25,
        "high": 155.67,
        "quarter": "2024 Q4",
        "source": "yahoo"
      },
      "allTime": {
        "avg": 100.6,
        "quarters": 12,
        "first": "2023 Q2",
        "last": "2026 Q1"
      }
    },
    "LRCX": {
      "recent": {
        "buy": 137.93,
        "low": 130.65,
        "high": 179.58,
        "quarter": "2025 Q4",
        "source": "yahoo"
      },
      "allTime": {
        "avg": 53.36,
        "quarters": 15,
        "first": "2018 Q1",
        "last": "2026 Q1"
      }
    },
    "BIDU": {
      "recent": {
        "buy": 114.84,
        "low": 105.77,
        "high": 165.3,
        "quarter": "2026 Q1",
        "source": "yahoo"
      },
      "allTime": {
        "avg": 97.09,
        "quarters": 13,
        "first": "2021 Q1",
        "last": "2026 Q1"
      }
    },
    "LHX": {
      "recent": {
        "buy": 201.65,
        "low": 191.65,
        "high": 253.68,
        "quarter": "2025 Q2",
        "source": "yahoo"
      },
      "allTime": {
        "avg": 239.69,
        "quarters": 5,
        "first": "2025 Q1",
        "last": "2026 Q1"
      }
    },
    "RTX": {
      "recent": {
        "buy": 116.13,
        "low": 109.95,
        "high": 146.92,
        "quarter": "2025 Q2",
        "source": "yahoo"
      },
      "allTime": {
        "avg": 146.97,
        "quarters": 4,
        "first": "2025 Q2",
        "last": "2026 Q1"
      }
    },
    "ASML": {
      "recent": {
        "buy": 1200.89,
        "low": 1129.52,
        "high": 1543.85,
        "quarter": "2026 Q1",
        "source": "yahoo"
      },
      "allTime": {
        "avg": 1320.83,
        "quarters": 1,
        "first": "2026 Q1",
        "last": "2026 Q1"
      }
    },
    "QCOM": {
      "recent": {
        "buy": 145.44,
        "low": 141.14,
        "high": 171.81,
        "quarter": "2025 Q3",
        "source": "yahoo"
      },
      "allTime": {
        "avg": 111.39,
        "quarters": 21,
        "first": "2016 Q3",
        "last": "2026 Q1"
      }
    },
    "BALL": {
      "recent": {
        "buy": 45.66,
        "low": 44.35,
        "high": 53.13,
        "quarter": "2025 Q4",
        "source": "yahoo"
      },
      "allTime": {
        "avg": 49.28,
        "quarters": 2,
        "first": "2025 Q4",
        "last": "2026 Q1"
      }
    },
    "AMD": {
      "recent": {
        "buy": 125.81,
        "low": 117.9,
        "high": 174.05,
        "quarter": "2024 Q4",
        "source": "yahoo"
      },
      "allTime": {
        "avg": 119.55,
        "quarters": 10,
        "first": "2023 Q2",
        "last": "2026 Q1"
      }
    },
    "JD": {
      "recent": {
        "buy": 32.68,
        "low": 31.1,
        "high": 44.85,
        "quarter": "2024 Q4",
        "source": "yahoo"
      },
      "allTime": {
        "avg": 28.73,
        "quarters": 11,
        "first": "2023 Q2",
        "last": "2026 Q1"
      }
    },
    "LYFT": {
      "recent": {
        "buy": 9.83,
        "low": 8.93,
        "high": 14.16,
        "quarter": "2024 Q3",
        "source": "yahoo"
      },
      "allTime": {
        "avg": 12.4,
        "quarters": 9,
        "first": "2024 Q1",
        "last": "2026 Q1"
      }
    },
    "MSFT": {
      "recent": {
        "buy": 473.57,
        "low": 462.83,
        "high": 550.24,
        "quarter": "2025 Q4",
        "source": "yahoo"
      },
      "allTime": {
        "avg": 324.57,
        "quarters": 25,
        "first": "2020 Q1",
        "last": "2026 Q1"
      }
    },
    "KWEB": {
      "recent": {
        "buy": 32.64,
        "low": 31.51,
        "high": 40.22,
        "quarter": "2025 Q3",
        "source": "yahoo"
      },
      "allTime": {
        "avg": 28.07,
        "quarters": 9,
        "first": "2024 Q1",
        "last": "2026 Q1"
      }
    },
    "ET": {
      "recent": {
        "buy": 16.02,
        "low": 15.33,
        "high": 19.22,
        "quarter": "2025 Q1",
        "source": "yahoo"
      },
      "allTime": {
        "avg": 7.22,
        "quarters": 30,
        "first": "2018 Q4",
        "last": "2026 Q1"
      }
    },
    "MPLX": {
      "recent": {
        "buy": 46.43,
        "low": 45.02,
        "high": 54.12,
        "quarter": "2025 Q4",
        "source": "yahoo"
      },
      "allTime": {
        "avg": 28.98,
        "quarters": 22,
        "first": "2020 Q4",
        "last": "2026 Q1"
      }
    },
    "UNH": {
      "recent": {
        "buy": 281.38,
        "low": 242.05,
        "high": 589.73,
        "quarter": "2025 Q2",
        "source": "yahoo"
      },
      "allTime": {
        "avg": 274.0,
        "quarters": 37,
        "first": "2017 Q1",
        "last": "2026 Q1"
      }
    },
    "DB": {
      "recent": {
        "buy": 29.21,
        "low": 27.13,
        "high": 39.01,
        "quarter": "2026 Q1",
        "source": "yahoo"
      },
      "allTime": {
        "avg": 29.78,
        "quarters": 1,
        "first": "2026 Q1",
        "last": "2026 Q1"
      }
    }
  }
}